dialogform/__init__.py
dialogform/apps.py
dialogform/forms.py
dialogform/tests.py
dialogform/views.py
dialogform/demo/__init__.py
dialogform/demo/admin.py
dialogform/demo/apps.py
dialogform/demo/asgi.py
dialogform/demo/db.sqlite3
dialogform/demo/forms.py
dialogform/demo/models.py
dialogform/demo/settings.py
dialogform/demo/tests.py
dialogform/demo/urls.py
dialogform/demo/views.py
dialogform/demo/wsgi.py
dialogform/static/dialogform/css/dialogform.css
dialogform/static/dialogform/demo/css/additional.css
dialogform/static/dialogform/demo/css/style.css
dialogform/static/dialogform/demo/img/favicon.ico
dialogform/static/dialogform/demo/img/icon-tag.svg
dialogform/static/dialogform/demo/js/additional.js
dialogform/static/dialogform/demo/js/admin_cleanup.js
dialogform/static/dialogform/demo/js/search.js
dialogform/static/dialogform/js/dialogform.js
dialogform/templates/dialogform/anchor_media.html
dialogform/templates/dialogform/dialog.html
dialogform/templates/dialogform/form.html
dialogform/templates/dialogform/page.html
dialogform/templates/dialogform/demo/admin_note_change.html
dialogform/templates/dialogform/demo/note_form.html
dialogform/templates/dialogform/demo/note_list.html
django_dialogform-1.1.dist-info/licenses/LICENSE
django_dialogform-1.1.dist-info/METADATA
django_dialogform-1.1.dist-info/WHEEL
django_dialogform-1.1.dist-info/top_level.txt
django_dialogform-1.1.dist-info/RECORD
