Metadata-Version: 2.4
Name: django-dialogform
Version: 1.1
Summary: Django app to load and open form views within dialog element popups
Author-email: Zoltan Kemenczy <gugliposta@gmail.com>
License-Expression: GPL-3.0-or-later
Project-URL: homepage, https://github.com/zoltan-ky/django-dialogform
Project-URL: repository, https://github.com/zoltan-ky/django-dialogform
Keywords: dialog,form,django
Classifier: Development Status :: 5 - Production/Stable
Classifier: Environment :: Web Environment
Classifier: Framework :: Django
Classifier: Framework :: Django :: 6
Classifier: Framework :: Django :: 5
Classifier: Intended Audience :: Developers
Classifier: Operating System :: OS Independent
Classifier: Programming Language :: Python
Classifier: Programming Language :: Python :: 3
Classifier: Programming Language :: JavaScript
Classifier: Topic :: Internet :: WWW/HTTP :: Dynamic Content
Requires-Python: >=3.8
License-File: LICENSE
Requires-Dist: django>=5.0
Dynamic: license-file
